{
  "concerts": [
    {
      "title": "第117回定期演奏会",
      "date": "2026-12-12",
      "dateLabel": "2026年12月12日（土）",
      "time": "17:30 開演",
      "venue": "すみだトリフォニーホール",
      "conductor": "決まり次第掲載いたします。",
      "program": [
        "決まり次第掲載いたします。"
      ],
      "ticketInfo": [
        "販売開始時期・料金は決まり次第掲載いたします。"
      ],
      "note": "曲目・チケット情報は決まり次第掲載いたします。",
      "image": "assets/8022.JPG",
      "imageAlt": "本番ステージで演奏する立教大学交響楽団",
      "ticketLabel": "チケット販売サイト準備中",
      "year": 2026
    },
    {
      "title": "第65回同立交歓演奏会",
      "date": "2026-06-15",
      "dateLabel": "2026年6月15日",
      "year": 2026,
      "venue": "東京芸術劇場",
      "conductor": "記録を確認中",
      "program": [
        "記録を確認中"
      ],
      "note": "同志社交響楽団さんとの合同演奏会が、大盛会の中終演いたしました。\nお越しくださったみなさま、誠にありがとうございました。"
    },
    {
      "title": "立教大学交響楽団 第116回定期演奏会",
      "date": "2025-10-31",
      "dateLabel": "2025年10月31日",
      "year": 2025,
      "venue": "東京芸術劇場 コンサートホール",
      "conductor": "記録を確認中",
      "program": [
        "記録を確認中"
      ],
      "note": "2025年度の自主公演として開催。",
      "image": "assets/IMG_8814.JPG",
      "imageAlt": "立教大学交響楽団 第116回定期演奏会のチラシ",
      "imageClass": "archive-concert-visual--topcrop"
    },
    {
      "title": "2025年度同立交歓演奏会 東京公演",
      "date": "2025-07-03",
      "dateLabel": "2025年7月3日",
      "year": 2025,
      "venue": "サントリーホール",
      "conductor": "記録を確認中",
      "program": [
        "記録を確認中"
      ],
      "note": "同志社交響楽団との合同による東京公演。",
      "image": "assets/IMG_8815.JPG",
      "imageAlt": "2025年度同立交歓演奏会 東京公演のチラシ"
    },
    {
      "title": "第64回同立交歓演奏会 京都公演",
      "date": "2025-06-15",
      "dateLabel": "2025年6月15日",
      "year": 2025,
      "venue": "京都コンサートホール",
      "conductor": "記録を確認中",
      "program": [
        "記録を確認中"
      ],
      "note": "同志社交響楽団との合同で行われた京都公演。",
      "image": "assets/2025_douritsu (1).jpg",
      "imageAlt": "第64回同立交歓演奏会 京都公演のチラシ"
    },
    {
      "title": "第115回定期演奏会",
      "date": "2024-11-06",
      "dateLabel": "2024年11月6日",
      "year": 2024,
      "venue": "オペラシティコンサートホール",
      "note": "指揮：尾高忠明\n曲目\nブルックナー：交響曲第4番\nワーグナー：歌劇「ローエングリン」より第1幕への前奏曲/第3幕への前奏曲",
      "image": "assets/創部105周年記念演奏会.jpg",
      "imageAlt": "第115回定期演奏会のチラシ"
    },
    {
      "title": "第63回同立交歓演奏会",
      "date": "2024-06-15",
      "dateLabel": "2024年6月15日",
      "year": 2024,
      "venue": "東京芸術劇場",
      "note": "指揮：山上絋生(立教)\n石崎真弥奈(同志社)\n曲目\nフランク：交響曲ニ短調（立教）\nブラームス：交響曲第1番（同志社）\nホルスト：組曲「惑星」より木星（合同曲）"
    },
    {
      "title": "2023年度卒業記念演奏会",
      "date": "2023-02-20",
      "dateLabel": "2023年2月20日",
      "year": 2023,
      "venue": "北とぴあ さくらホール",
      "note": "指揮：家田厚志\n曲目\nショスタコーヴィチ：交響曲第5番\nサン=サーンス：交響詩「死の舞踏」"
    },
    {
      "title": "第114回定期演奏会",
      "date": "2023-11-02",
      "dateLabel": "2023年11月2日",
      "year": 2023,
      "venue": "東京芸術劇場",
      "note": "指揮：出口大地\n曲目\nラフマニノフ：交響曲第2番\nハチャトゥリアン：組曲「仮面舞踏会」"
    },
    {
      "title": "2023年度同立交歓演奏会東京公演",
      "date": "",
      "dateLabel": "日程記録なし",
      "year": 2023,
      "venue": "東京芸術劇場",
      "note": "指揮：田中一嘉\n曲目\nドヴォルザーク：交響曲第8番\nボロディン：歌劇「イーゴリ公」より『ダッタン人の踊り』"
    },
    {
      "title": "2022年度卒業記念演奏会",
      "date": "2022-02-20",
      "dateLabel": "2022年2月20日",
      "year": 2022,
      "venue": "北とぴあ さくらホール",
      "note": "指揮：山上紘生\n曲目\nドヴォルザーク：交響曲第9番\nグリーグ：ノルウェー舞曲"
    },
    {
      "title": "第113回定期演奏会",
      "date": "2022-11-23",
      "dateLabel": "2022年11月23日",
      "year": 2022,
      "venue": "東京芸術劇場",
      "note": "指揮：山上純司\n曲目\nシベリウス：交響曲第1番\nチャイコフスキー：幻想序曲「ロメオとジュリエット」\nワーグナー：歌劇「リエンツィ」序曲"
    },
    {
      "title": "同立交歓演奏会",
      "date": "2022-06-10",
      "dateLabel": "2022年6月10日",
      "year": 2022,
      "venue": "東京芸術劇場",
      "note": "指揮：田中一嘉(立教)\n大山平一郎(同志社)\n曲目\nチャイコフスキー：交響曲第5番（立教）\nドヴォルザーク：交響曲第9番（同志社）\nブラームス：大学祝典序曲（合同曲）"
    },
    {
      "title": "2021年度卒業記念演奏会",
      "date": "2022-02-25",
      "dateLabel": "2022年2月25日（金）",
      "year": 2021,
      "venue": "なかのZERO大ホール",
      "note": "指揮：家田厚志\n曲目\nワーグナー：楽劇『ニュルンベルクのマイスタージンガー』より 第一幕への前奏曲\nチャイコフスキー：交響曲第６番ロ短調 作品74『悲愴』"
    },
    {
      "title": "第112回定期演奏会",
      "date": "2021-11-06",
      "dateLabel": "2021年11月6日（土）",
      "year": 2021,
      "venue": "東京芸術劇場",
      "note": "指揮：山上紘生\n曲目\nドヴォルザーク：序曲「謝肉祭」作品92\nチャイコフスキー：バレエ組曲「くるみ割り人形」Op71a\nグラズノフ：交響曲第５番ロ長調 作品55"
    },
    {
      "title": "東京演奏会",
      "date": "2021-06-27",
      "dateLabel": "2021年6月27日（日）",
      "year": 2021,
      "venue": "東京芸術劇場",
      "note": "指揮：田中一嘉\n曲目\nビゼー：カルメン組曲より抜粋\nブラームス：交響曲第２番ニ長調 作品73"
    },
    {
      "title": "第111回定期演奏会",
      "date": "2020-11-11",
      "dateLabel": "2020年11月11日（水）",
      "year": 2020,
      "venue": "東京芸術劇場",
      "note": "指揮：秋山和慶\n曲目：チャイコフスキー：交響曲第4番ヘ短調 作品36\nシューベルト：交響曲第7(8)番「未完成」\nシベリウス：交響詩「フィンランディア」Op26"
    },
    {
      "title": "2019年度卒業記念演奏会",
      "date": "2020-02-21",
      "dateLabel": "2020年2月21日（金）",
      "year": 2019,
      "venue": "なかのZERO大ホール",
      "note": "指揮：家田厚志\nヴァイオリン：村尾隆人（2018年度立教大学交響楽団コンサートマスター）\n曲目：チャイコフスキー：ヴァイオリン協奏曲ニ長調作品35\nシベリウス：交響曲第2番ニ長調作品43"
    },
    {
      "title": "立教大学交響楽団創部100周年記念 第110回定期演奏会",
      "date": "2019-11-08",
      "dateLabel": "2019年11月8日（金）",
      "year": 2019,
      "venue": "東京芸術劇場 大ホール",
      "note": "指揮：尾高忠明\nピアノ：北村朋幹\n曲目：ショスタコーヴィチ：交響曲第5番\nラフマニノフ：ピアノ協奏曲第2番\nリャードフ：キキモラ"
    },
    {
      "title": "2019年度東京演奏会",
      "date": "2019-06-29",
      "dateLabel": "2019年6月29日（土）",
      "year": 2019,
      "venue": "東京芸術劇場 大ホール",
      "note": "指揮：山上純司\n曲目：ドヴォルザーク：交響曲第8番\nボロディン：歌劇「イーゴリ公」より『ダッタン人の娘たちの踊り』『ダッタン人の踊り』"
    },
    {
      "title": "2018年度卒業記念演奏会",
      "date": "2019-02-22",
      "dateLabel": "2019年2月22日（金）",
      "year": 2018,
      "venue": "なかのZERO大ホール",
      "note": "指揮：田中一嘉\n曲目：ドヴォルザーク：交響曲第9番ホ短調作品95「新世界より」\nチャイコフスキー：幻想序曲「ロミオとジュリエット」"
    },
    {
      "title": "第109回定期演奏会",
      "date": "2018-11-10",
      "dateLabel": "2018年11月10日（土）",
      "year": 2018,
      "venue": "東京芸術劇場 大ホール",
      "note": "指揮：田中一嘉\nオルガン：高橋博子\n曲目：サン=サーンス：交響曲第3番｢オルガン付き｣\nブラームス：ハイドンの主題による変奏曲\nエルガー：序曲｢コケイン｣"
    },
    {
      "title": "2018年度同立交歓演奏",
      "date": "2018-07-07",
      "dateLabel": "2018年7月7日(土)",
      "year": 2018,
      "venue": "すみだトリフォニーホール大ホール",
      "note": "指揮：家田厚志（立教）\n新田ユリ（同志社）\n曲目：チャイコフスキー：交響曲第5番（立教）\nドヴォルザーク：交響曲第6番（同志社）\nリムスキー＝コルサコフ：スペイン奇想曲（合同曲）"
    },
    {
      "title": "2017年度卒業記念演奏会",
      "date": "2018-02-16",
      "dateLabel": "2018年2月16日(金)",
      "year": 2017,
      "venue": "杉並公会堂",
      "note": "指揮：木全利行\n曲目：カリンニコフ：交響曲第1番\nベートーヴェン：交響曲第8番"
    },
    {
      "title": "第108回定期演奏会",
      "date": "2017-11-05",
      "dateLabel": "2017年11月5日(日)",
      "year": 2017,
      "venue": "東京芸術劇場 大ホール",
      "note": "指揮：田中一嘉\n曲目：シベリウス：交響曲第1番\nチャイコフスキー：バレエ組曲「くるみ割り人形」\nベートーベン：「フィデリオ」序曲"
    },
    {
      "title": "2017年度東京演奏会",
      "date": "2017-06-23",
      "dateLabel": "2017年6月23日(金)",
      "year": 2017,
      "venue": "東京芸術劇場 大ホール",
      "note": "指揮：海老原 光\n曲目：ドヴォルザーク：交響曲第7番\nリスト：「前奏曲」"
    },
    {
      "title": "2016年度卒業記念演奏会",
      "date": "2017-02-22",
      "dateLabel": "2017年2月22日(水)",
      "year": 2016,
      "venue": "記録なし",
      "note": "指揮：田中一嘉\n曲目：ブラームス：交響曲第2番\nシューベルト：交響曲第7番「未完成」"
    },
    {
      "title": "第107回定期演奏会",
      "date": "2016-11-11",
      "dateLabel": "2016年11月11日(金)",
      "year": 2016,
      "venue": "東京芸術劇場 大ホール",
      "note": "指揮：田中一嘉\n曲目：ラフマニノフ：交響曲第2番\nスメタナ：連作交響詩「我が祖国」よりモルダウ\nベートーヴェン：劇音楽「エグモント」序曲"
    },
    {
      "title": "第55回同立交歓演奏会",
      "date": "2016-06-25",
      "dateLabel": "2016年6月25日(土)",
      "year": 2016,
      "venue": "東京芸術劇場 大ホール",
      "note": "指揮:山下一史（立教）齊藤一郎（同志社）\n曲目:チャイコフスキー：交響曲第4番（立教）\nドヴォルザーク：交響曲第9番（同志社）他"
    },
    {
      "title": "2015年度卒業演奏会",
      "date": "2016-02-19",
      "dateLabel": "2016年2月19日（金）",
      "year": 2015,
      "venue": "練馬文化センター大ホール",
      "note": "指揮:田中一嘉\n曲目:ブラームス：交響曲第4番\nチャイコフスキー：「眠れる森の美女」組曲"
    },
    {
      "title": "第106回定期演奏会",
      "date": "2015-11-07",
      "dateLabel": "2015年11月7日(土)",
      "year": 2015,
      "venue": "東京芸術劇場 大ホール",
      "note": "指揮:田中一嘉\n曲目:シベリウス：交響曲第２番\nエルガー：エニグマ変奏曲\nヴェルディ：歌劇 『運命の力』序曲"
    },
    {
      "title": "東京演奏会",
      "date": "2015-06-27",
      "dateLabel": "2015年6月27日(土)",
      "year": 2015,
      "venue": "東京芸術劇場 大ホール",
      "note": "指揮:安斎拓志\n曲目:ドヴォルザーク：交響曲第８番\nワーグナー：歌劇「タンホイザー」序曲"
    },
    {
      "title": "2014年度卒業記念演奏会",
      "date": "2015-02-20",
      "dateLabel": "2015年2月20日(金)",
      "year": 2014,
      "venue": "めぐろパーシモンホール",
      "note": "指揮:木全利行\n曲目:チャイコフスキー：交響曲第６番「悲愴」\nブラームス：大学祝典序曲"
    },
    {
      "title": "立教学院創立140周年 立教大学交響楽団創部95周年 第105回定期演奏会",
      "date": "2014-11-09",
      "dateLabel": "2014年11月9日(日)",
      "year": 2014,
      "venue": "サントリーホール",
      "note": "指揮:現田茂夫\n独奏:清水和音(ピアノ)\n曲目:マーラー：交響曲第１番「巨人」\nチャイコフスキー：ピアノ協奏曲第１番\nワーグナー：楽劇「ニュルンベルクのマイスタージンガー」より前奏曲"
    },
    {
      "title": "第53回同立交歓演奏会",
      "date": "2014-06-15",
      "dateLabel": "2014年6月15日(日)",
      "year": 2014,
      "venue": "東京芸術劇場 コンサートホール",
      "note": "指揮:田中一嘉(立教) 小田野宏之(同志社)\n曲目:ブラームス：交響曲第２番(同志社)\nチャイコフスキー：交響曲第５番(立教)\nチャイコフスキー：序曲「１８１２年」(合同曲)"
    },
    {
      "title": "2013年度卒業記念演奏会",
      "date": "2014-02-23",
      "dateLabel": "2014年2月23日(日)",
      "year": 2013,
      "venue": "新宿文化センター 大ホール",
      "note": "指揮:田中一嘉\nベートーヴェン：交響曲第７番\nビゼー：交響曲"
    },
    {
      "title": "第104回定期演奏会",
      "date": "2013-11-08",
      "dateLabel": "2013年11月8日(金)",
      "year": 2013,
      "venue": "東京芸術劇場 コンサートホール",
      "note": "指揮:田尻真高\nベルリオーズ：幻想交響曲\nドリーブ：バレエ「コッペリア」より抜粋\nウェーバー：歌劇「オベロン」序曲"
    },
    {
      "title": "東京演奏会",
      "date": "2013-06-29",
      "dateLabel": "2013年6月29日(土)",
      "year": 2013,
      "venue": "東京芸術劇場 コンサートホール",
      "note": "指揮:田中一嘉\nドヴォルザーク：交響曲第7番\nチャイコフスキー：幻想序曲「ロメオとジュリエット」"
    },
    {
      "title": "第52回同立交歓演奏会",
      "date": "2013-06-15",
      "dateLabel": "2013年6月15日(土)",
      "year": 2013,
      "venue": "京都コンサートホール",
      "note": "指揮:田中一嘉(立教) 松元宏康(同志社)\nドヴォルザーク：交響曲第７番(立教)\nドヴォルザーク：交響曲第８番(同志社)\nチャイコフスキー：スラブ行進曲(合同曲)"
    },
    {
      "title": "2012年度卒業記念演奏会",
      "date": "2013-02-24",
      "dateLabel": "2013年2月24日(日)",
      "year": 2012,
      "venue": "和光市民文化センター サンアゼリア 大ホール",
      "note": "指揮:田中一嘉\nショスタコービッチ：交響曲第５番 ニ短調 作品47\nワーグナー：トリスタンとイゾルデ 前奏曲と愛の死"
    },
    {
      "title": "第103回定期演奏会",
      "date": "2012-11-11",
      "dateLabel": "2012年11月11日(日)",
      "year": 2012,
      "venue": "杉並公会堂 大ホール",
      "note": "指揮:田中一嘉\nラフマニノフ：交響曲第2曲\nリスト：交響詩「前奏曲」\nグリンカ：歌劇「ルスランとリュドミラ」序曲"
    },
    {
      "title": "第51回 同立交歓演奏会",
      "date": "2012-06-10",
      "dateLabel": "2012年6月10日(日)",
      "year": 2012,
      "venue": "東京文化会館 大ホール",
      "note": "指揮：小田野宏之(立教) 吉田行地(同志社)\nベートーヴェン：交響曲第５番〈運命〉(同志社)\nブラームス：交響曲第１番 (立教)\nチャイコフスキー：イタリア奇想曲(合同曲)"
    },
    {
      "title": "2011年度卒業記念演奏会",
      "date": "2012-02-25",
      "dateLabel": "2012年2月25日(土)",
      "year": 2011,
      "venue": "めぐろパーシモンホール 大ホール",
      "note": "指揮:田中一嘉\nドヴォルザーク:交響曲第9番＜新世界より＞\nチャイコフスキー:「1812年」"
    },
    {
      "title": "第102回定期演奏会",
      "date": "2011-11-04",
      "dateLabel": "2011年11月4日(金)",
      "year": 2011,
      "venue": "大田区民ホール アプリコ",
      "note": "指揮:家田厚志\nバルトーク:管弦楽のための協奏曲\nチャイコフスキー:「眠りの森の美女」より抜粋\nシューマン:「マンフレッド」 序曲"
    },
    {
      "title": "東京演奏会",
      "date": "2011-06-24",
      "dateLabel": "2011年6月24日(金)",
      "year": 2011,
      "venue": "文京シビック 大ホール",
      "note": "指揮:田中一嘉\nチャイコフスキー:交響曲第4番 ヘ短調作品36\nハチャトゥリアン:バレエ組曲「ガイーヌ」より抜粋 剣の舞、レズギンカ他"
    },
    {
      "title": "第50回同立交歓演奏会",
      "date": "2011-06-18",
      "dateLabel": "2011年6月18日(土)",
      "year": 2011,
      "venue": "京都コンサートホール 大ホール",
      "note": "指揮:小田野宏之(同志社) 田中一嘉(立教)\nチャイコフスキー:交響曲第4番 ヘ短調作品36(立教)\nチャイコフスキー:交響曲第5番 ホ短調作品64(同志社)\nブラームス:大学祝典序曲 ハ短調作品80(合同曲)"
    },
    {
      "title": "2010年度卒業記念演奏会",
      "date": "2011-02-25",
      "dateLabel": "2011年2月25日(金)",
      "year": 2010,
      "venue": "かつしかシンフォニーヒルズ",
      "note": "指揮：茂木大輔\nシューベルト:交響曲第8番ハ長調「ザ・グレート」\nチャイコフスキー:バレエ組曲「くるみ割り人形」"
    },
    {
      "title": "2010年度卒業記念演奏会 仙台特別演奏会",
      "date": "2011-02-23",
      "dateLabel": "2011年2月23日(水)",
      "year": 2010,
      "venue": "仙台市青年文化センター",
      "note": "指揮:茂木大輔\nチャイコフスキー:交響曲第4番 ヘ短調作品36\nチャイコフスキー:バレエ組曲「くるみ割り人形」"
    },
    {
      "title": "第101回定期演奏会",
      "date": "2010-11-13",
      "dateLabel": "2010年11月13日（月）",
      "year": 2010,
      "venue": "東京芸術劇場 大ホール",
      "note": "指揮：宮松重紀\nチャイコフスキー:交響曲第1番≪冬の日の幻想≫\nチャイコフスキー:「白鳥の湖」より抜粋\nボロディン:歌劇「イーゴリ公」序曲"
    },
    {
      "title": "第49回同立交歓演奏会",
      "date": "2010-06-20",
      "dateLabel": "2010年6月20日（日）",
      "year": 2010,
      "venue": "東京芸術劇場 大ホール",
      "note": "指揮：田中一嘉(立教)\n金洪才(同志社)\nブラームス:交響曲第4番(立教)\nブラームス:交響曲第2番(同志社)\nワーグナー:「ニュルンベルクのマイスタージンガー」より前奏曲(合同曲)"
    },
    {
      "title": "立教学院創立135年 立教大学交響楽団創部90周年 第100回定期演奏会",
      "date": "2009-11-08",
      "dateLabel": "2009年11月8日",
      "year": 2009,
      "venue": "サントリーホール",
      "note": "指揮：広上淳一\n独奏・ゲストコンサートマスター：チャールズ・ウェザビー(Vn)\nベルリオーズ：ローマの謝肉祭\nコルンゴルド：ヴァイオリン協奏曲\nベルリオーズ：幻想交響曲"
    },
    {
      "title": "東京演奏会",
      "date": "2009-06-28",
      "dateLabel": "2009年6月28日（日）",
      "year": 2009,
      "venue": "東京芸術劇場 大ホール",
      "note": "指揮：池田俊\nグリーグ：ペールギュント第１組曲/第２組曲\nブラームス：交響曲第３番"
    },
    {
      "title": "第48回 同立交歓演奏会",
      "date": "2009-06-02",
      "dateLabel": "2009年6月2日",
      "year": 2009,
      "venue": "京都コンサートホール",
      "note": "指揮：新田ユリ(同志社) 池田俊(立教)\nドヴォルザーク：交響曲第７番（同志社）\nブラームス  ：交響曲第３番（立教）\nブラームス  ：ハンガリー舞曲第１０番・１７番（合同）\nドヴォルザーク：スラヴ舞曲第３番・８番"
    },
    {
      "title": "卒業記念演奏会",
      "date": "2009-02-28",
      "dateLabel": "2009年2月28日",
      "year": 2008,
      "venue": "江戸川区総合文化センター",
      "note": "指揮：田中一嘉\nワーグナー：ワルキューレの騎行\nジークフリート牧歌\nチャイコフスキー：交響曲第５番"
    },
    {
      "title": "第９９回 定期演奏会",
      "date": "2008-11-09",
      "dateLabel": "2008年11月9日（日）",
      "year": 2008,
      "venue": "すみだトリフォニーホール",
      "note": "指揮：田代俊文\nオルガン：室住素子\nベルリオーズ ：序曲「海賊」\nリスト    ：交響詩「前奏曲」(レ・プレリュード)\nサン＝サーンス：交響曲第３番「オルガン付」"
    },
    {
      "title": "第４７回 同立交歓演奏会",
      "date": "2008-06-22",
      "dateLabel": "2008年6月22日（日）",
      "year": 2008,
      "venue": "東京芸術劇場 大ホール",
      "note": "指揮：小田野宏之（同志社）\n田中一嘉（立教＋合同曲）\nブラームス：交響曲第１番（同志社）\nチャイコフスキー：交響曲第６番『悲愴』（立教）\nチャイコフスキー：序曲『１８１２年』（同立合同演奏）"
    },
    {
      "title": "卒業記念演奏会",
      "date": "2008-02-29",
      "dateLabel": "2008年2月29日",
      "year": 2007,
      "venue": "品川区総合区民会館きゅりあん",
      "note": "指揮：石川真也\nチャイコフスキー：イタリア奇想曲\nブラームス：交響曲第４番"
    },
    {
      "title": "第９８回 定期演奏会",
      "date": "2007-11-02",
      "dateLabel": "2007年11月2日",
      "year": 2007,
      "venue": "東京芸術劇場",
      "note": "指揮：田中一嘉\nシューマン：『マンフレッド』序曲\nドリーブ：バレエ音楽『コッペリア』より\nエルガー：交響曲第１番"
    },
    {
      "title": "東京演奏会",
      "date": "2007-07-08",
      "dateLabel": "2007年7月8日",
      "year": 2007,
      "venue": "昭和女子大学人見記念講堂",
      "note": "指揮：橘直貴\n独奏：山本裕康（チェロ）\nベートーヴェン：『コリオラン』序曲\nエルガー：チェロ協奏曲\nブラームス：交響曲第２番"
    },
    {
      "title": "第４６回 同立交歓演奏会（京都）",
      "date": "2007-06-16",
      "dateLabel": "2007年6月16日",
      "year": 2007,
      "venue": "京都コンサートホール",
      "note": "指揮：橘直貴（立教）\n金洪才（同志社＋合同曲）\nベートーヴェン：交響曲第５番『運命』（同志社）\nブラームス：交響曲第２番（立教）\nブラームス：大学祝典序曲（同立合同演奏）"
    },
    {
      "title": "第９７回 定期演奏会",
      "date": "2006-11-11",
      "dateLabel": "2006年11月11日",
      "year": 2006,
      "venue": "すみだトリフォニーホール",
      "note": "指揮：小田野宏之\nショスタコーヴィチ：祝典序曲\nチャイコフスキー：組曲『くるみ割り人形』\nラフマニノフ：交響曲第２番"
    },
    {
      "title": "第４５回 同立交歓演奏会（東京）",
      "date": "2006-06-25",
      "dateLabel": "2006年6月25日",
      "year": 2006,
      "venue": "東京芸術劇場",
      "note": "指揮：田中一嘉（立教＋合同曲）\n小田野宏之（同志社)\nドヴォルザーク：交響曲第７番（立教）\nドヴォルザーク：交響曲第８番（同志社）\nチャイコフスキー：スラヴ行進曲（同立合同演奏）"
    },
    {
      "title": "第９６回 定期演奏会",
      "date": "2005-11-03",
      "dateLabel": "2005年11月3日",
      "year": 2005,
      "venue": "すみだトリフォニーホール",
      "note": "指揮：新通英洋\n独唱：佐々木典子（ソプラノ）\nモーツァルト：歌劇『フィガロの結婚』序曲\nＲ．シュトラウス：四つの最後の唄\nマーラー：交響曲第１番『巨人』"
    },
    {
      "title": "東京演奏会",
      "date": "2005-06-11",
      "dateLabel": "2005年6月11日",
      "year": 2005,
      "venue": "東京芸術劇場",
      "note": "指揮：田中一嘉\n独奏：大谷康子（東京交響楽団コンサートマスター）\nチャイコフスキー：交響曲第５番\nメンデルスゾーン：ヴァイオリン協奏曲ホ短調\nワーグナー：『ニュルンベルクのマイスタージンガー』より前奏曲"
    },
    {
      "title": "第４４回 同立交歓演奏会（京都）",
      "date": "2005-06-05",
      "dateLabel": "2005年6月5日",
      "year": 2005,
      "venue": "京都コンサートホール",
      "note": "指揮：田中一嘉（立教）\n新田ユリ（同志社＋合同曲）\nチャイコフスキー：交響曲第５番（立教）\nブラームス：交響曲第３番（同志社）\nボロディン：歌劇『イーゴリ公』よりダッタン人の踊り（同立合同演奏）"
    },
    {
      "title": "卒業演奏会",
      "date": "2005-03-04",
      "dateLabel": "2005年3月4日",
      "year": 2004,
      "venue": "大田区民ホール アプリコ",
      "note": "指揮：須藤信也\nベートーヴェン：『エグモント』序曲\nドヴォルザーク：交響曲第９番「新世界より」"
    },
    {
      "title": "第９５回 定期演奏会",
      "date": "2004-11-06",
      "dateLabel": "2004年11月6日",
      "year": 2004,
      "venue": "東京芸術劇場",
      "note": "指揮：新通英洋\nサン＝サーンス：歌劇『サムソンとデリラ』よりバッカナール\nバーンスタイン：『ウエストサイドストーリー』よりシンフォニックダンス\nブラームス：交響曲第４番"
    },
    {
      "title": "立教学院創立130周年立教大学交響楽団創部85周年記念演奏会",
      "date": "2004-08-23",
      "dateLabel": "2004年8月23日",
      "year": 2004,
      "venue": "サントリーホール 大ホール",
      "note": "指揮：小松一彦\nＪ．シュトラウス：喜歌劇「こうもり」序曲（現役・ＯＢ合同）\nドヴォルザーク：チェロ協奏曲（ＯＢ）\nシベリウス：交響曲第２番（現役）"
    },
    {
      "title": "第４３回 同立交歓演奏会（東京）",
      "date": "2004-06-20",
      "dateLabel": "2004年6月20日",
      "year": 2004,
      "venue": "東京芸術劇場",
      "note": "指揮：橘直貴（立教＋合同曲）\n斉藤一郎（同志社）\nドヴォルザーク：交響曲第９番『新世界』より（同志社）\nシベリウス：交響曲第２番（立教）\nハチャトゥリアン：組曲「仮面舞踏会」（同立合同演奏）"
    },
    {
      "title": "卒業演奏会",
      "date": "2004-03-05",
      "dateLabel": "2004年3月5日",
      "year": 2003,
      "venue": "大田区民ホール アプリコ",
      "note": "指揮：新通英洋\nボロディン：歌劇「イーゴリ公」よりダッタン人の踊り\nベートーヴェン：交響曲第5番 運命"
    },
    {
      "title": "第９４回 定期演奏会",
      "date": "2003-11-22",
      "dateLabel": "2003年11月22日",
      "year": 2003,
      "venue": "東京芸術劇場",
      "note": "指揮：吉田裕史\nサン＝サーンス：交響曲第３番ハ短調『オルガン付き』\nチャイコフスキー：幻想序曲『ロメオとジュリエット』\nムソルグスキー：交響詩『禿山の一夜』"
    },
    {
      "title": "第４２回 同立交歓演奏会（京都）",
      "date": "2003-06-21",
      "dateLabel": "2003年6月21日",
      "year": 2003,
      "venue": "京都コンサートホール",
      "note": "指揮：田中一嘉（立教）\n小田野宏之（同志社＋合同曲）\nドヴォルザーク：交響曲８番（立教）\nベートーヴェン：『プロメテウスの創造物』より序曲（同志社）\nシューマン：交響曲４番（同志社）\nファリャ：バレエ音楽『三角帽子』より終幕の踊り（同立合同演奏）"
    },
    {
      "title": "東京演奏会",
      "date": "2003-06-08",
      "dateLabel": "2003年6月8日",
      "year": 2003,
      "venue": "東京芸術劇場",
      "note": "指揮：田中一嘉\nビゼー：組曲『カルメン』より抜粋\nＪ.シュトラウス：喜歌劇『こうもり』序曲\nドヴォルザーク：交響曲第８番"
    },
    {
      "title": "卒業演奏会",
      "date": "2003-03-02",
      "dateLabel": "2003年3月2日",
      "year": 2002,
      "venue": "中野ZEROホール",
      "note": "指揮：吉田裕史\nブラームス：大学祝典序曲\nチャイコフスキー：交響曲第５番"
    },
    {
      "title": "第９３回 定期演奏会",
      "date": "2002-11-04",
      "dateLabel": "2002年11月4日",
      "year": 2002,
      "venue": "東京芸術劇場",
      "note": "指揮：新通英洋\nスメタナ：交響詩『わが祖国』よりモルダウ\nサン＝サーンス：死の舞踏\nショスタコーヴィチ：交響曲第５番"
    },
    {
      "title": "第４１回 同立交歓演奏会（東京）",
      "date": "2002-06-22",
      "dateLabel": "2002年6月22日",
      "year": 2002,
      "venue": "文京シビックホール",
      "note": "指揮：藤崎凡（立教＋合同曲）\n新田ユリ（同志社）\nベートーヴェン：交響曲第５番（同志社）\nブラームス：交響曲第２番（立教）\nドヴォルザーク：謝肉祭（合同演奏）"
    }
  ]
}
